[
  {
    "id": 1,
    "sku": "309-sns-546-S-WHE",
    "title_lang1": "Lamb - Whole, Fresh",
    "group_id": "",
    "group": ""
  },
  {
    "id": 2,
    "sku": "198-irc-334-M-WHE",
    "title_lang1": "Bread - Kimel Stick Poly",
    "group_id": "",
    "group": ""
  },
  {
    "id": 3,
    "sku": "633-nrv-453-L-WHE",
    "title_lang1": "Beans - Soya Bean",
    "group_id": "",
    "group": ""
  },
  {
    "id": 4,
    "sku": "597-cig-301-L-LIN",
    "title_lang1": "Oil - Truffle, White",
    "group_id": "",
    "group": ""
  },
  {
    "id": 5,
    "sku": "358-qvj-315-M-LIN",
    "title_lang1": "Initation Crab Meat",
    "group_id": "",
    "group": ""
  },
  {
    "id": 6,
    "sku": "301-tkk-746-S-LIN",
    "title_lang1": "Mushroom - Enoki, Dry",
    "group_id": "",
    "group": ""
  },
  {
    "id": 7,
    "sku": "669-xeq-091-S-ARE",
    "title_lang1": "Pepper - Chillies, Crushed",
    "group_id": "",
    "group": ""
  },
  {
    "id": 8,
    "sku": "390-qfh-429-L-ARE",
    "title_lang1": "Bread - Roll, Italian",
    "group_id": "",
    "group": ""
  },
  {
    "id": 9,
    "sku": "284-fsr-952-M-ARE",
    "title_lang1": "Juice - Lime",
    "group_id": "",
    "group": ""
  },
  {
    "id": 10,
    "sku": "890-zbp-256-L-BLK",
    "title_lang1": "Table Cloth 72x144 White",
    "group_id": "",
    "group": ""
  },
  {
    "id": 11,
    "sku": "200-lqc-672-L-WHE",
    "title_lang1": "Pepper - Black, Crushed"
  },
  {
    "id": 12,
    "sku": "334-dyq-421-S-LIN",
    "title_lang1": "Ginger - Fresh",
    "group_id": "",
    "group": ""
  },
  {
    "id": 13,
    "sku": "680-qcu-209-S-LIN",
    "title_lang1": "Artichoke - Hearts, Canned",
    "group": ""
  },
  {
    "id": 14,
    "sku": "387-qol-700-S-LIN",
    "title_lang1": "Cheese - Brick With Onion",
    "group_id": "",
    "group": ""
  },
  {
    "id": 15,
    "sku": "478-qrp-894-S-LIN",
    "title_lang1": "Salt - Rock, Course",
    "group_id": "",
    "group": ""
  },
  {
    "id": 16,
    "sku": "202-zuq-153-S-ARN",
    "title_lang1": "Sauce - Balsamic Viniagrette",
    "group_id": "",
    "group": ""
  },
  {
    "id": 17,
    "sku": "809-sam-748-S-ARN",
    "title_lang1": "Cookies - Fortune",
    "group_id": "",
    "group": ""
  },
  {
    "id": 18,
    "sku": "653-mog-533-S-ARN",
    "title_lang1": "Sparkling Wine - Rose, Freixenet",
    "group_id": "",
    "group": ""
  },
  {
    "id": 19,
    "sku": "854-gra-342-L-WHE",
    "title_lang1": "Beer - Tetleys",
    "group_id": "",
    "group": ""
  },
  {
    "id": 20,
    "sku": "544-iua-343-L-WHE",
    "title_lang1": "Muffin Mix - Raisin Bran",
    "group_id": "", 
    "group": ""
  }
]